netbox_sb_dc_accessdata/__init__.py
netbox_sb_dc_accessdata/filtersets.py
netbox_sb_dc_accessdata/forms.py
netbox_sb_dc_accessdata/graphql.py
netbox_sb_dc_accessdata/models.py
netbox_sb_dc_accessdata/navigation.py
netbox_sb_dc_accessdata/tables.py
netbox_sb_dc_accessdata/urls.py
netbox_sb_dc_accessdata/views.py
netbox_sb_dc_accessdata/api/__init__.py
netbox_sb_dc_accessdata/api/serializers.py
netbox_sb_dc_accessdata/api/urls.py
netbox_sb_dc_accessdata/api/views.py
netbox_sb_dc_accessdata/migrations/0001_initial.py
netbox_sb_dc_accessdata/migrations/__init__.py
netbox_sb_dc_accessdata/templates/netbox_sb_dc_accessdata/key.html
netbox_sb_dc_accessdata/templates/netbox_sb_dc_accessdata/keycard.html
netbox_sb_dc_accessdata-1.1.dist-info/LICENSE
netbox_sb_dc_accessdata-1.1.dist-info/METADATA
netbox_sb_dc_accessdata-1.1.dist-info/WHEEL
netbox_sb_dc_accessdata-1.1.dist-info/top_level.txt
netbox_sb_dc_accessdata-1.1.dist-info/RECORD
